lucidity_files/__init__.py
lucidity_files/file_utils.py
lucidity_files/lucidity_files.py
lucidity_files-0.1.2.dist-info/LICENSE
lucidity_files-0.1.2.dist-info/METADATA
lucidity_files-0.1.2.dist-info/WHEEL
lucidity_files-0.1.2.dist-info/top_level.txt
lucidity_files-0.1.2.dist-info/RECORD
