Metadata-Version: 2.1
Name: lucidity_files
Version: 0.1.2
Summary: List files with lucidity templates.
Author-email: Eduardo Grana <eduardo@eduardograna.com>
License: MIT License
Project-URL: Homepage, https://gitlab.com/eduardograna/lucidity_files
Keywords: templates,files,listing
Classifier: License :: OSI Approved :: MIT License
Classifier: Programming Language :: Python
Classifier: Programming Language :: Python :: 3
Classifier: Programming Language :: Python :: 2
Classifier: Development Status :: 4 - Beta
Classifier: Intended Audience :: Developers
Classifier: Operating System :: Microsoft :: Windows
Classifier: Topic :: System :: Filesystems
Requires-Python: >=2.7
License-File: LICENSE
Requires-Dist: lucidity >=1.6.0
